[{"key": "/main/actions/autofocus", "label": "Auto-Focus", "ro": "0", "Current": "2", "choices": []}, {"key": "/main/actions/capture", "label": "Capture", "ro": "0", "Current": "2", "choices": []}, {"key": "/main/actions/bulb", "label": "Bulb Mode", "ro": "0", "Current": "2", "choices": []}, {"key": "/main/actions/movie", "label": "Movie Capture", "ro": "0", "Current": "2", "choices": []}, {"key": "/main/actions/opcode", "label": "PTP Opcode", "ro": "0", "Current": "0x1001,0xparam1,0xparam2", "choices": []}, {"key": "/main/status/serialnumber", "label": "Serial Number", "ro": "0", "Current": "00000000000000003282793003859549", "choices": []}, {"key": "/main/status/manufacturer", "label": "Camera Manufacturer", "ro": "0", "Current": "Sony Corporation", "choices": []}, {"key": "/main/status/cameramodel", "label": "Camera Model", "ro": "0", "Current": "ILCE-7M2", "choices": []}, {"key": "/main/status/deviceversion", "label": "Device Version", "ro": "0", "Current": "4.0", "choices": []}, {"key": "/main/status/vendorextension", "label": "Vendor Extension", "ro": "0", "Current": "Sony PTP Extensions", "choices": []}, {"key": "/main/status/batterylevel", "label": "Battery Level", "ro": "0", "Current": "86%", "choices": []}, {"key": "/main/imgsettings/imagesize", "label": "Image Size", "ro": "0", "Current": "Large", "choices": [["0", " Large"], ["1", " Medium"], ["2", " Small"]]}, {"key": "/main/imgsettings/iso", "label": "ISO Speed", "ro": "0", "Current": "Auto ISO", "choices": [["0", " Auto ISO"], ["1", " 50"], ["2", " 64"], ["3", " 80"], ["4", " 100"], ["5", " 125"], ["6", " 160"], ["7", " 200"], ["8", " 250"], ["9", " 320"], ["10", " 400"], ["11", " 500"], ["12", " 640"], ["13", " 800"], ["14", " 1000"], ["15", " 1250"], ["16", " 1600"], ["17", " 2000"], ["18", " 2500"], ["19", " 3200"], ["20", " 4000"], ["21", " 5000"], ["22", " 6400"], ["23", " 8000"], ["24", " 10000"], ["25", " 12800"], ["26", " 16000"], ["27", " 20000"], ["28", " 25600"], ["29", " 32000"], ["30", " 40000"], ["31", " 51200"], ["32", " 64000"], ["33", " 80000"], ["34", " 102400"], ["35", " 128000"], ["36", " 160000"], ["37", " 204800"], ["38", " 256000"], ["39", " 320000"], ["40", " 409600"], ["41", " Auto ISO Multi Frame Noise Reduction"], ["42", " 100 Multi Frame Noise Reduction"], ["43", " 200 Multi Frame Noise Reduction"], ["44", " 400 Multi Frame Noise Reduction"], ["45", " 800 Multi Frame Noise Reduction"], ["46", " 1600 Multi Frame Noise Reduction"], ["47", " 3200 Multi Frame Noise Reduction"], ["48", " 6400 Multi Frame Noise Reduction"], ["49", " 12800 Multi Frame Noise Reduction"], ["50", " 25600 Multi Frame Noise Reduction"], ["51", " 51200 Multi Frame Noise Reduction"], ["52", " 36864 Multi Frame Noise Reduction"], ["53", " 8192 Multi Frame Noise Reduction"], ["54", " 16384 Multi Frame Noise Reduction"]]}, {"key": "/main/imgsettings/colortemperature", "label": "Color Temperature", "ro": "0", "Current": "0", "choices": []}, {"key": "/main/imgsettings/whitebalance", "label": "WhiteBalance", "ro": "0", "Current": "Automatic", "choices": [["0", " Automatic"], ["1", " Daylight"], ["2", " Shade"], ["3", " Cloudy"], ["4", " Tungsten"], ["5", " Fluorescent: Warm White"], ["6", " Fluorescent: Cold White"], ["7", " Fluorescent: Day White"], ["8", " Fluorescent: Daylight"], ["9", " Flash"], ["10", " Underwater: Auto"], ["11", " Choose Color Temperature"], ["12", " Preset 1"], ["13", " Preset 2"], ["14", " Preset 3"]]}, {"key": "/main/capturesettings/exposurecompensation", "label": "Exposure Compensation", "ro": "0", "Current": "0", "choices": [["0", " 0"], ["1", " 0.001"], ["2", " 0.002"], ["3", " 5"], ["4", " 4.7"], ["5", " 4.5"], ["6", " 4.3"], ["7", " 4"], ["8", " 3.7"], ["9", " 3.5"], ["10", " 3.3"], ["11", " 3"], ["12", " 2.7"], ["13", " 2.5"], ["14", " 2.3"], ["15", " 2"], ["16", " 1.7"], ["17", " 1.5"], ["18", " 1.3"], ["19", " 1"], ["20", " 0.7"], ["21", " 0.5"], ["22", " 0.3"], ["23", " -0.3"], ["24", " -0.5"], ["25", " -0.7"], ["26", " -1"], ["27", " -1.3"], ["28", " -1.5"], ["29", " -1.7"], ["30", " -2"], ["31", " -2.3"], ["32", " -2.5"], ["33", " -2.7"], ["34", " -3"], ["35", " -3.3"], ["36", " -3.5"], ["37", " -3.7"], ["38", " -4"], ["39", " -4.3"], ["40", " -4.5"], ["41", " -4.7"], ["42", " -5"]]}, {"key": "/main/capturesettings/flashmode", "label": "Flash Mode", "ro": "0", "Current": "Unknown value 0000", "choices": [["0", " Flash off"], ["1", " Automatic Flash"], ["2", " Red-eye automatic"], ["3", " Fill flash"], ["4", " Red-eye fill"], ["5", " Unknown value 8001"], ["6", " Rear Curtain Sync"], ["7", " Wireless Sync"], ["8", " Unknown value 8031"], ["9", " Slow Sync"], ["10", " Unknown value 0000"]]}, {"key": "/main/capturesettings/f-number", "label": "F-Number", "ro": "0", "Current": "0", "choices": []}, {"key": "/main/capturesettings/imagequality", "label": "Image Quality", "ro": "0", "Current": "RAW", "choices": [["0", " Standard"], ["1", " Fine"], ["2", " Extra Fine"], ["3", " RAW"], ["4", " RAW+JPEG"]]}, {"key": "/main/capturesettings/focusmode", "label": "Focus Mode", "ro": "0", "Current": "Manual", "choices": [["0", " Manual"], ["1", " Automatic"], ["2", " AF-C"], ["3", " AF-A"], ["4", " DMF"]]}, {"key": "/main/capturesettings/expprogram", "label": "Exposure Program", "ro": "0", "Current": "A", "choices": [["0", " Intelligent Auto"], ["1", " Superior Auto"], ["2", " P"], ["3", " A"], ["4", " S"], ["5", " M"], ["6", " Movie"], ["7", " Unknown value 8051"], ["8", " Unknown value 8052"], ["9", " Unknown value 8053"], ["10", " Unknown value 8054"], ["11", " Sweep Panorama"], ["12", " Portrait"], ["13", " Sports Action"], ["14", " Macro"], ["15", " Landscape"], ["16", " Sunset"], ["17", " Night Scene"], ["18", " Hand-held Twilight"], ["19", " Night Portrait"], ["20", " Unknown value 8018"]]}, {"key": "/main/capturesettings/aspectratio", "label": "Aspect Ratio", "ro": "0", "Current": "3:2", "choices": [["0", " 3:2"], ["1", " 16:9"]]}, {"key": "/main/capturesettings/capturemode", "label": "Still Capture Mode", "ro": "0", "Current": "Single Shot", "choices": [["0", " Single Shot"], ["1", " Burst"], ["2", " Continuous Low Speed"], ["3", " Selftimer 2s"], ["4", " Selftimer 10s"], ["5", " Selftimer 10s 3 Pictures"], ["6", " Selftimer 10s 5 Pictures"], ["7", " Bracketing C 0.3 Steps 3 Pictures"], ["8", " Bracketing C 0.3 Steps 5 Pictures"], ["9", " Bracketing C 0.5 Steps 3 Pictures"], ["10", " Bracketing C 0.5 Steps 5 Pictures"], ["11", " Bracketing C 0.7 Steps 3 Pictures"], ["12", " Bracketing C 0.7 Steps 5 Pictures"], ["13", " Bracketing C 1.0 Steps 3 Pictures"], ["14", " Bracketing C 1.0 Steps 5 Pictures"], ["15", " Bracketing C 2.0 Steps 3 Pictures"], ["16", " Bracketing C 2.0 Steps 5 Pictures"], ["17", " Bracketing C 3.0 Steps 3 Pictures"], ["18", " Bracketing C 3.0 Steps 5 Pictures"], ["19", " Bracketing S 0.3 Steps 3 Pictures"], ["20", " Bracketing S 0.3 Steps 5 Pictures"], ["21", " Bracketing S 0.5 Steps 3 Pictures"], ["22", " Bracketing S 0.5 Steps 5 Pictures"], ["23", " Bracketing S 0.7 Steps 3 Pictures"], ["24", " Bracketing S 0.7 Steps 5 Pictures"], ["25", " Bracketing S 1.0 Steps 3 Pictures"], ["26", " Bracketing S 1.0 Steps 5 Pictures"], ["27", " Bracketing S 2.0 Steps 3 Pictures"], ["28", " Bracketing S 2.0 Steps 5 Pictures"], ["29", " Bracketing S 3.0 Steps 3 Pictures"], ["30", " Bracketing S 3.0 Steps 5 Pictures"], ["31", " Bracketing WB Lo"], ["32", " Bracketing WB Hi"], ["33", " Bracketing DRO Lo"], ["34", " Bracketing DRO Hi"]]}, {"key": "/main/capturesettings/exposuremetermode", "label": "Exposure Metering Mode", "ro": "0", "Current": "Average", "choices": [["0", " Center Spot"], ["1", " Average"], ["2", " Unknown value 8002"]]}, {"key": "/main/capturesettings/shutterspeed", "label": "Shutter Speed", "ro": "0", "Current": "1/60", "choices": [["0", " 30"], ["1", " 25"], ["2", " 20"], ["3", " 15"], ["4", " 13"], ["5", " 10"], ["6", " 8"], ["7", " 6"], ["8", " 5"], ["9", " 4"], ["10", " 32/10"], ["11", " 25/10"], ["12", " 2"], ["13", " 16/10"], ["14", " 13/10"], ["15", " 1"], ["16", " 8/10"], ["17", " 6/10"], ["18", " 5/10"], ["19", " 4/10"], ["20", " 1/3"], ["21", " 1/4"], ["22", " 1/5"], ["23", " 1/6"], ["24", " 1/8"], ["25", " 1/10"], ["26", " 1/13"], ["27", " 1/15"], ["28", " 1/20"], ["29", " 1/25"], ["30", " 1/30"], ["31", " 1/40"], ["32", " 1/50"], ["33", " 1/60"], ["34", " 1/80"], ["35", " 1/100"], ["36", " 1/125"], ["37", " 1/160"], ["38", " 1/200"], ["39", " 1/250"], ["40", " 1/320"], ["41", " 1/400"], ["42", " 1/500"], ["43", " 1/640"], ["44", " 1/800"], ["45", " 1/1000"], ["46", " 1/1250"], ["47", " 1/1600"], ["48", " 1/2000"], ["49", " 1/2500"], ["50", " 1/3200"], ["51", " 1/4000"], ["52", " Bulb"]]}, {"key": "/main/other/5004", "label": "Compression Setting", "ro": "0", "Current": "16", "choices": [["0", " 2"], ["1", " 3"], ["2", " 4"], ["3", " 16"], ["4", " 19"]]}, {"key": "/main/other/5005", "label": "White Balance", "ro": "0", "Current": "2", "choices": [["0", " 2"], ["1", " 4"], ["2", " 32785"], ["3", " 32784"], ["4", " 6"], ["5", " 32769"], ["6", " 32770"], ["7", " 32771"], ["8", " 32772"], ["9", " 7"], ["10", " 32816"], ["11", " 32786"], ["12", " 32800"], ["13", " 32801"], ["14", " 32802"]]}, {"key": "/main/other/5007", "label": "F-Number", "ro": "0", "Current": "0", "choices": []}, {"key": "/main/other/500a", "label": "Focus Mode", "ro": "0", "Current": "1", "choices": [["0", " 1"], ["1", " 2"], ["2", " 32772"], ["3", " 32773"], ["4", " 32774"]]}, {"key": "/main/other/500b", "label": "Exposure Metering Mode", "ro": "0", "Current": "1", "choices": [["0", " 4"], ["1", " 1"], ["2", " 32770"]]}, {"key": "/main/other/500c", "label": "Flash Mode", "ro": "0", "Current": "0", "choices": [["0", " 2"], ["1", " 1"], ["2", " 4"], ["3", " 3"], ["4", " 5"], ["5", " 32769"], ["6", " 32771"], ["7", " 32772"], ["8", " 32817"], ["9", " 32818"]]}, {"key": "/main/other/500e", "label": "Exposure Program Mode", "ro": "0", "Current": "3", "choices": [["0", " 32768"], ["1", " 32769"], ["2", " 2"], ["3", " 3"], ["4", " 4"], ["5", " 1"], ["6", " 32848"], ["7", " 32849"], ["8", " 32850"], ["9", " 32851"], ["10", " 32852"], ["11", " 32833"], ["12", " 7"], ["13", " 32785"], ["14", " 32789"], ["15", " 32788"], ["16", " 32786"], ["17", " 32787"], ["18", " 32790"], ["19", " 32791"], ["20", " 32792"]]}, {"key": "/main/other/5010", "label": "Exposure Bias Compensation", "ro": "0", "Current": "0", "choices": [["0", " 0"], ["1", " 1"], ["2", " 2"], ["3", " 5000"], ["4", " 4700"], ["5", " 4500"], ["6", " 4300"], ["7", " 4000"], ["8", " 3700"], ["9", " 3500"], ["10", " 3300"], ["11", " 3000"], ["12", " 2700"], ["13", " 2500"], ["14", " 2300"], ["15", " 2000"], ["16", " 1700"], ["17", " 1500"], ["18", " 1300"], ["19", " 1000"], ["20", " 700"], ["21", " 500"], ["22", " 300"], ["23", " -300"], ["24", " -500"], ["25", " -700"], ["26", " -1000"], ["27", " -1300"], ["28", " -1500"], ["29", " -1700"], ["30", " -2000"], ["31", " -2300"], ["32", " -2500"], ["33", " -2700"], ["34", " -3000"], ["35", " -3300"], ["36", " -3500"], ["37", " -3700"], ["38", " -4000"], ["39", " -4300"], ["40", " -4500"], ["41", " -4700"], ["42", " -5000"]]}, {"key": "/main/other/5013", "label": "Still Capture Mode", "ro": "0", "Current": "1", "choices": [["0", " 1"], ["1", " 2"], ["2", " 32786"], ["3", " 32773"], ["4", " 32772"], ["5", " 32776"], ["6", " 32777"], ["7", " 33591"], ["8", " 34103"], ["9", " 33623"], ["10", " 34135"], ["11", " 33655"], ["12", " 34167"], ["13", " 33553"], ["14", " 34065"], ["15", " 33569"], ["16", " 34081"], ["17", " 33585"], ["18", " 34097"], ["19", " 33590"], ["20", " 34102"], ["21", " 33622"], ["22", " 34134"], ["23", " 33654"], ["24", " 34166"], ["25", " 33552"], ["26", " 34064"], ["27", " 33568"], ["28", " 34080"], ["29", " 33584"], ["30", " 34096"], ["31", " 32792"], ["32", " 32808"], ["33", " 32793"], ["34", " 32809"]]}, {"key": "/main/other/d200", "label": "DOC Compensation", "ro": "0", "Current": "0", "choices": [["0", " 0"], ["1", " 1"], ["2", " 2"], ["3", " 3000"], ["4", " 2700"], ["5", " 2500"], ["6", " 2300"], ["7", " 2000"], ["8", " 1700"], ["9", " 1500"], ["10", " 1300"], ["11", " 1000"], ["12", " 700"], ["13", " 500"], ["14", " 300"], ["15", " -300"], ["16", " -500"], ["17", " -700"], ["18", " -1000"], ["19", " -1300"], ["20", " -1500"], ["21", " -1700"], ["22", " -2000"], ["23", " -2300"], ["24", " -2500"], ["25", " -2700"], ["26", " -3000"]]}, {"key": "/main/other/d201", "label": "DRangeOptimize", "ro": "0", "Current": "1", "choices": [["0", " 1"], ["1", " 31"], ["2", " 17"], ["3", " 18"], ["4", " 19"], ["5", " 20"], ["6", " 21"]]}, {"key": "/main/other/d203", "label": "Image size", "ro": "0", "Current": "1", "choices": [["0", " 1"], ["1", " 2"], ["2", " 3"]]}, {"key": "/main/other/d20d", "label": "Shutter speed", "ro": "0", "Current": "65596", "choices": []}, {"key": "/main/other/d20e", "label": "PTP Property 0xd20e", "ro": "0", "Current": "7", "choices": [["0", " 1"], ["1", " 2"], ["2", " 3"], ["3", " 8"], ["4", " 9"], ["5", " 10"], ["6", " 4"], ["7", " 5"], ["8", " 6"], ["9", " 7"]]}, {"key": "/main/other/d20f", "label": "Color temperature", "ro": "0", "Current": "0", "choices": []}, {"key": "/main/other/d210", "label": "CC Filter", "ro": "0", "Current": "128", "choices": [["0", " 121"], ["1", " 122"], ["2", " 123"], ["3", " 124"], ["4", " 125"], ["5", " 126"], ["6", " 127"], ["7", " 128"], ["8", " 129"], ["9", " 130"], ["10", " 131"], ["11", " 132"], ["12", " 133"], ["13", " 134"], ["14", " 135"]]}, {"key": "/main/other/d21c", "label": "AB Filter", "ro": "0", "Current": "128", "choices": [["0", " 121"], ["1", " 122"], ["2", " 123"], ["3", " 124"], ["4", " 125"], ["5", " 126"], ["6", " 127"], ["7", " 128"], ["8", " 129"], ["9", " 130"], ["10", " 131"], ["11", " 132"], ["12", " 133"], ["13", " 134"], ["14", " 135"]]}, {"key": "/main/other/d211", "label": "Aspect Ratio", "ro": "0", "Current": "1", "choices": [["0", " 1"], ["1", " 2"]]}, {"key": "/main/other/d213", "label": "Focus status", "ro": "0", "Current": "1", "choices": [["0", " 1"], ["1", " 2"], ["2", " 3"], ["3", " 5"], ["4", " 6"], ["5", " 7"]]}, {"key": "/main/other/d21e", "label": "ISO", "ro": "0", "Current": "16777215", "choices": [["0", " 16777215"], ["1", " 50"], ["2", " 64"], ["3", " 80"], ["4", " 100"], ["5", " 125"], ["6", " 160"], ["7", " 200"], ["8", " 250"], ["9", " 320"], ["10", " 400"], ["11", " 500"], ["12", " 640"], ["13", " 800"], ["14", " 1000"], ["15", " 1250"], ["16", " 1600"], ["17", " 2000"], ["18", " 2500"], ["19", " 3200"], ["20", " 4000"], ["21", " 5000"], ["22", " 6400"], ["23", " 8000"], ["24", " 10000"], ["25", " 12800"], ["26", " 16000"], ["27", " 20000"], ["28", " 25600"], ["29", " 32000"], ["30", " 40000"], ["31", " 51200"], ["32", " 64000"], ["33", " 80000"], ["34", " 102400"], ["35", " 128000"], ["36", " 160000"], ["37", " 204800"], ["38", " 256000"], ["39", " 320000"], ["40", " 409600"], ["41", " 33554431"], ["42", " 16777316"], ["43", " 16777416"], ["44", " 16777616"], ["45", " 16778016"], ["46", " 16778816"], ["47", " 16780416"], ["48", " 16783616"], ["49", " 16790016"], ["50", " 16802816"], ["51", " 16828416"], ["52", " 16879616"], ["53", " 16982016"], ["54", " 17186816"]]}, {"key": "/main/other/d21b", "label": "Picture Effect", "ro": "0", "Current": "32768", "choices": [["0", " 32768"]]}, {"key": "/main/other/d21d", "label": "PTP Property 0xd21d", "ro": "0", "Current": "0", "choices": [["0", " 0"], ["1", " 1"], ["2", " 2"]]}, {"key": "/main/other/d21f", "label": "PTP Property 0xd21f", "ro": "0", "Current": "1", "choices": [["0", " 2"], ["1", " 1"]]}, {"key": "/main/other/d217", "label": "PTP Property 0xd217", "ro": "0", "Current": "1", "choices": [["0", " 2"], ["1", " 1"]]}, {"key": "/main/other/d218", "label": "Battery Level", "ro": "0", "Current": "86", "choices": [["0", " -1"], ["1", " 0"], ["2", " 1"], ["3", " 2"], ["4", " 3"], ["5", " 4"], ["6", " 5"], ["7", " 6"], ["8", " 7"], ["9", " 8"], ["10", " 9"], ["11", " 10"], ["12", " 11"], ["13", " 12"], ["14", " 13"], ["15", " 14"], ["16", " 15"], ["17", " 16"], ["18", " 17"], ["19", " 18"], ["20", " 19"], ["21", " 20"], ["22", " 21"], ["23", " 22"], ["24", " 23"], ["25", " 24"], ["26", " 25"], ["27", " 26"], ["28", " 27"], ["29", " 28"], ["30", " 29"], ["31", " 30"], ["32", " 31"], ["33", " 32"], ["34", " 33"], ["35", " 34"], ["36", " 35"], ["37", " 36"], ["38", " 37"], ["39", " 38"], ["40", " 39"], ["41", " 40"], ["42", " 41"], ["43", " 42"], ["44", " 43"], ["45", " 44"], ["46", " 45"], ["47", " 46"], ["48", " 47"], ["49", " 48"], ["50", " 49"], ["51", " 50"], ["52", " 51"], ["53", " 52"], ["54", " 53"], ["55", " 54"], ["56", " 55"], ["57", " 56"], ["58", " 57"], ["59", " 58"], ["60", " 59"], ["61", " 60"], ["62", " 61"], ["63", " 62"], ["64", " 63"], ["65", " 64"], ["66", " 65"], ["67", " 66"], ["68", " 67"], ["69", " 68"], ["70", " 69"], ["71", " 70"], ["72", " 71"], ["73", " 72"], ["74", " 73"], ["75", " 74"], ["76", " 75"], ["77", " 76"], ["78", " 77"], ["79", " 78"], ["80", " 79"], ["81", " 80"], ["82", " 81"], ["83", " 82"], ["84", " 83"], ["85", " 84"], ["86", " 85"], ["87", " 86"], ["88", " 87"], ["89", " 88"], ["90", " 89"], ["91", " 90"], ["92", " 91"], ["93", " 92"], ["94", " 93"], ["95", " 94"], ["96", " 95"], ["97", " 96"], ["98", " 97"], ["99", " 98"], ["100", " 99"], ["101", " 100"]]}, {"key": "/main/other/d219", "label": "PTP Property 0xd219", "ro": "0", "Current": "1", "choices": [["0", " 2"], ["1", " 1"]]}, {"key": "/main/other/d212", "label": "PTP Property 0xd212", "ro": "0", "Current": "0", "choices": [["0", " 0"], ["1", " 1"], ["2", " 2"], ["3", " 3"], ["4", " 4"], ["5", " 5"], ["6", " 6"], ["7", " 7"], ["8", " 8"], ["9", " 9"], ["10", " 10"], ["11", " 11"], ["12", " 12"], ["13", " 13"], ["14", " 14"], ["15", " 15"]]}, {"key": "/main/other/d221", "label": "PTP Property 0xd221", "ro": "0", "Current": "1", "choices": [["0", " 0"], ["1", " 1"], ["2", " 2"]]}, {"key": "/main/other/d214", "label": "PTP Property 0xd214", "ro": "0", "Current": "3.422e+07", "choices": []}, {"key": "/main/other/d215", "label": "Objects in memory", "ro": "0", "Current": "0", "choices": []}, {"key": "/main/other/d2c1", "label": "PTP Property 0xd2c1", "ro": "0", "Current": "1", "choices": [["0", " 1"], ["1", " 2"]]}, {"key": "/main/other/d2c2", "label": "PTP Property 0xd2c2", "ro": "0", "Current": "1", "choices": [["0", " 1"], ["1", " 2"]]}, {"key": "/main/other/d2c3", "label": "PTP Property 0xd2c3", "ro": "0", "Current": "1", "choices": [["0", " 1"], ["1", " 2"]]}, {"key": "/main/other/d2c9", "label": "PTP Property 0xd2c9", "ro": "0", "Current": "1", "choices": [["0", " 1"], ["1", " 2"]]}, {"key": "/main/other/d2c8", "label": "Movie", "ro": "0", "Current": "1", "choices": [["0", " 1"], ["1", " 2"]]}, {"key": "/main/other/d2c5", "label": "PTP Property 0xd2c5", "ro": "0", "Current": "1", "choices": [["0", " 1"], ["1", " 2"]]}, {"key": "/main/other/d2c7", "label": "Still Image", "ro": "0", "Current": "1", "choices": [["0", " 1"], ["1", " 2"]]}]